{
  "id": "04-小鱼易连融合云视频平台技术白皮书V1.1-sec-260",
  "doc_file": "04-小鱼易连融合云视频平台技术白皮书V1.1.bin",
  "title": "媒体交换网络保证音视频的近似可靠传输。在网络突发异常，例如丢包、拥塞时，仍可保证音视频能以较好的质量分发到会议中的各个终端。",
  "path": "媒体交换网络保证音视频的近似可靠传输。在网络突发异常，例如丢包、拥塞时，仍可保证音视频能以较好的质量分发到会议中的各个终端。",
  "level": 2,
  "line_start": 677,
  "char_count": 0,
  "tags": [
    "architecture",
    "stability"
  ],
  "body": "",
  "related_topics": [
    "stability"
  ],
  "aliases": [
    "可靠性保障",
    "稳定保障",
    "高可用",
    "高可靠"
  ],
  "sibling_sections": [],
  "source_weight": 2
}