{
  "id": "04-小鱼易连融合云视频平台技术白皮书V1.1-sec-103",
  "doc_file": "04-小鱼易连融合云视频平台技术白皮书V1.1.bin",
  "title": "Ticket服务：工单服务，为客户提供工单相关的功能，包括查询工单、创建和修改管理工单的服务。",
  "path": "Ticket服务：工单服务，为客户提供工单相关的功能，包括查询工单、创建和修改管理工单的服务。",
  "level": 2,
  "line_start": 419,
  "char_count": 111,
  "tags": [
    "architecture"
  ],
  "body": "* + 1. **通讯录服务子模块**\n\n通讯录服务子模块主要为为各个企业提供组织架构形式的人员及设备管理方式，以及为各种不同类型的终端（硬终端，软终端） 提供设备通讯录，以及为其他服务提供组织架构人员、设备相关查询接口。",
  "related_topics": [],
  "aliases": [],
  "sibling_sections": [],
  "source_weight": 2
}