{
  "id": "06-新一代视频会议系统建设方案模板-sec-029",
  "doc_file": "06-新一代视频会议系统建设方案模板.bin",
  "title": "系统性能需求分析",
  "path": "需求分析 > 系统性能需求分析",
  "level": 2,
  "line_start": 139,
  "char_count": 0,
  "tags": [],
  "body": "",
  "related_topics": [],
  "aliases": [],
  "sibling_sections": [
    "06-新一代视频会议系统建设方案模板-sec-023",
    "06-新一代视频会议系统建设方案模板-sec-024",
    "06-新一代视频会议系统建设方案模板-sec-025",
    "06-新一代视频会议系统建设方案模板-sec-026",
    "06-新一代视频会议系统建设方案模板-sec-027",
    "06-新一代视频会议系统建设方案模板-sec-028",
    "06-新一代视频会议系统建设方案模板-sec-030",
    "06-新一代视频会议系统建设方案模板-sec-031"
  ],
  "source_weight": 3
}