{
  "id": "09-09-2026年私有云3月迭代版本新功能培训文档-云平台-sec-150",
  "doc_file": "09-2026年私有云3月迭代版本新功能培训文档-云平台.md",
  "title": "【功能说明】",
  "level": 2,
  "path": "研发同步内容 > 云平台功能 > 【功能说明】",
  "line_start": 1184,
  "char_count": 228,
  "body": "opsadmin登录Console会管平台后，选择菜单【备份与升级→数据备份与升级→更多配置→数据清理策略】，支持根据需要设置备份文件的保存时间（必填），仅能输入正整数数字，默认值30天，输入范围1-90。\n\n超过该保存时间的备份文件将自动被删除。\n\n修改文件保存时间后，系统不会立即执行删除任务，会在以下时间点进行删除：\n\n* 在每天自动备份任务中生效，即凌晨3:30\n* 手动进行数据备份时\n\n![](data:image/png;base64...)",
  "tags": [],
  "related_topics": [],
  "aliases": [],
  "sibling_sections": [],
  "source_weight": 2
}
