{
  "id": "17-17-小鱼易连风铃系统1月迭代新功能培训文档-sec-045",
  "doc_file": "17-小鱼易连风铃系统1月迭代新功能培训文档.md",
  "title": "l POPS 充值",
  "level": 2,
  "path": "文档密级：内部 > l POPS 充值",
  "line_start": 549,
  "char_count": 217,
  "body": "通过 POPS 购买 AI 相关并发后，高级模式下可见、可用相关功能。\n\n本期 POPS 增加**迭代版本控制**配置，\n\n• 对于 20250815 迭代以前版本，保持原有配置\n\n• 对于 20251212 迭代及以上版本，增加涉及语音转写、智能纪要、终端智能记会\n\n如 POPS 未填写语音转写、智能纪要、终端智能记会方数，导入后，Console 平台不展示对应方数。\n\n![](data:image/png;base64...)",
  "tags": [],
  "related_topics": [],
  "aliases": [],
  "sibling_sections": [],
  "source_weight": 2
}
